{
  "SessionStats": [
    {
      "TreasuresCollected": 22,
      "MaxLevelReached": 1,
      "EnemiesDefeated": 1,
      "FoodConsumed": 0,
      "ElixirsConsumed": 0,
      "ScrollsConsumed": 0,
      "HitsLanded": 8,
      "HitsMissed": 9,
      "HitsTaken": 39,
      "CellsMoved": 273
    },
    {
      "TreasuresCollected": 0,
      "MaxLevelReached": 3,
      "EnemiesDefeated": 0,
      "FoodConsumed": 0,
      "ElixirsConsumed": 0,
      "ScrollsConsumed": 0,
      "HitsLanded": 3,
      "HitsMissed": 1,
      "HitsTaken": 69,
      "CellsMoved": 323
    },
    {
      "TreasuresCollected": 0,
      "MaxLevelReached": 1,
      "EnemiesDefeated": 0,
      "FoodConsumed": 0,
      "ElixirsConsumed": 0,
      "ScrollsConsumed": 0,
      "HitsLanded": 6,
      "HitsMissed": 12,
      "HitsTaken": 13,
      "CellsMoved": 31
    },
    {
      "TreasuresCollected": 0,
      "MaxLevelReached": 1,
      "EnemiesDefeated": 0,
      "FoodConsumed": 0,
      "ElixirsConsumed": 0,
      "ScrollsConsumed": 0,
      "HitsLanded": 8,
      "HitsMissed": 6,
      "HitsTaken": 19,
      "CellsMoved": 197
    },
    {
      "TreasuresCollected": 0,
      "MaxLevelReached": 1,
      "EnemiesDefeated": 0,
      "FoodConsumed": 0,
      "ElixirsConsumed": 0,
      "ScrollsConsumed": 0,
      "HitsLanded": 7,
      "HitsMissed": 4,
      "HitsTaken": 21,
      "CellsMoved": 67
    },
    {
      "TreasuresCollected": 16,
      "MaxLevelReached": 1,
      "EnemiesDefeated": 1,
      "FoodConsumed": 0,
      "ElixirsConsumed": 0,
      "ScrollsConsumed": 0,
      "HitsLanded": 21,
      "HitsMissed": 14,
      "HitsTaken": 29,
      "CellsMoved": 93
    },
    {
      "TreasuresCollected": 0,
      "MaxLevelReached": 1,
      "EnemiesDefeated": 0,
      "FoodConsumed": 0,
      "ElixirsConsumed": 0,
      "ScrollsConsumed": 0,
      "HitsLanded": 7,
      "HitsMissed": 7,
      "HitsTaken": 10,
      "CellsMoved": 28
    },
    {
      "TreasuresCollected": 23,
      "MaxLevelReached": 2,
      "EnemiesDefeated": 1,
      "FoodConsumed": 0,
      "ElixirsConsumed": 0,
      "ScrollsConsumed": 0,
      "HitsLanded": 13,
      "HitsMissed": 9,
      "HitsTaken": 15,
      "CellsMoved": 238
    },
    {
      "TreasuresCollected": 10,
      "MaxLevelReached": 2,
      "EnemiesDefeated": 1,
      "FoodConsumed": 3,
      "ElixirsConsumed": 0,
      "ScrollsConsumed": 0,
      "HitsLanded": 12,
      "HitsMissed": 7,
      "HitsTaken": 22,
      "CellsMoved": 134
    },
    {
      "TreasuresCollected": 20,
      "MaxLevelReached": 5,
      "EnemiesDefeated": 2,
      "FoodConsumed": 6,
      "ElixirsConsumed": 3,
      "ScrollsConsumed": 0,
      "HitsLanded": 18,
      "HitsMissed": 16,
      "HitsTaken": 73,
      "CellsMoved": 401
    },
    {
      "TreasuresCollected": 0,
      "MaxLevelReached": 1,
      "EnemiesDefeated": 0,
      "FoodConsumed": 0,
      "ElixirsConsumed": 0,
      "ScrollsConsumed": 0,
      "HitsLanded": 7,
      "HitsMissed": 6,
      "HitsTaken": 22,
      "CellsMoved": 34
    },
    {
      "TreasuresCollected": 0,
      "MaxLevelReached": 2,
      "EnemiesDefeated": 0,
      "FoodConsumed": 6,
      "ElixirsConsumed": 3,
      "ScrollsConsumed": 4,
      "HitsLanded": 15,
      "HitsMissed": 12,
      "HitsTaken": 27,
      "CellsMoved": 396
    },
    {
      "TreasuresCollected": 0,
      "MaxLevelReached": 1,
      "EnemiesDefeated": 0,
      "FoodConsumed": 0,
      "ElixirsConsumed": 0,
      "ScrollsConsumed": 1,
      "HitsLanded": 9,
      "HitsMissed": 9,
      "HitsTaken": 11,
      "CellsMoved": 143
    },
    {
      "TreasuresCollected": 0,
      "MaxLevelReached": 1,
      "EnemiesDefeated": 0,
      "FoodConsumed": 0,
      "ElixirsConsumed": 0,
      "ScrollsConsumed": 1,
      "HitsLanded": 13,
      "HitsMissed": 9,
      "HitsTaken": 10,
      "CellsMoved": 146
    },
    {
      "TreasuresCollected": 0,
      "MaxLevelReached": 1,
      "EnemiesDefeated": 0,
      "FoodConsumed": 0,
      "ElixirsConsumed": 0,
      "ScrollsConsumed": 2,
      "HitsLanded": 8,
      "HitsMissed": 8,
      "HitsTaken": 11,
      "CellsMoved": 207
    },
    {
      "TreasuresCollected": 0,
      "MaxLevelReached": 1,
      "EnemiesDefeated": 0,
      "FoodConsumed": 0,
      "ElixirsConsumed": 0,
      "ScrollsConsumed": 1,
      "HitsLanded": 9,
      "HitsMissed": 6,
      "HitsTaken": 10,
      "CellsMoved": 176
    },
    {
      "TreasuresCollected": 0,
      "MaxLevelReached": 1,
      "EnemiesDefeated": 0,
      "FoodConsumed": 0,
      "ElixirsConsumed": 0,
      "ScrollsConsumed": 1,
      "HitsLanded": 8,
      "HitsMissed": 10,
      "HitsTaken": 11,
      "CellsMoved": 147
    },
    {
      "TreasuresCollected": 0,
      "MaxLevelReached": 1,
      "EnemiesDefeated": 0,
      "FoodConsumed": 0,
      "ElixirsConsumed": 0,
      "ScrollsConsumed": 1,
      "HitsLanded": 9,
      "HitsMissed": 11,
      "HitsTaken": 11,
      "CellsMoved": 147
    },
    {
      "TreasuresCollected": 0,
      "MaxLevelReached": 1,
      "EnemiesDefeated": 0,
      "FoodConsumed": 0,
      "ElixirsConsumed": 0,
      "ScrollsConsumed": 1,
      "HitsLanded": 8,
      "HitsMissed": 10,
      "HitsTaken": 11,
      "CellsMoved": 147
    },
    {
      "TreasuresCollected": 0,
      "MaxLevelReached": 1,
      "EnemiesDefeated": 0,
      "FoodConsumed": 0,
      "ElixirsConsumed": 0,
      "ScrollsConsumed": 1,
      "HitsLanded": 11,
      "HitsMissed": 11,
      "HitsTaken": 11,
      "CellsMoved": 147
    },
    {
      "TreasuresCollected": 0,
      "MaxLevelReached": 1,
      "EnemiesDefeated": 0,
      "FoodConsumed": 0,
      "ElixirsConsumed": 0,
      "ScrollsConsumed": 1,
      "HitsLanded": 9,
      "HitsMissed": 10,
      "HitsTaken": 11,
      "CellsMoved": 147
    },
    {
      "TreasuresCollected": 0,
      "MaxLevelReached": 1,
      "EnemiesDefeated": 0,
      "FoodConsumed": 0,
      "ElixirsConsumed": 0,
      "ScrollsConsumed": 1,
      "HitsLanded": 10,
      "HitsMissed": 9,
      "HitsTaken": 11,
      "CellsMoved": 147
    },
    {
      "TreasuresCollected": 0,
      "MaxLevelReached": 1,
      "EnemiesDefeated": 0,
      "FoodConsumed": 0,
      "ElixirsConsumed": 0,
      "ScrollsConsumed": 1,
      "HitsLanded": 9,
      "HitsMissed": 9,
      "HitsTaken": 11,
      "CellsMoved": 147
    },
    {
      "TreasuresCollected": 0,
      "MaxLevelReached": 1,
      "EnemiesDefeated": 0,
      "FoodConsumed": 0,
      "ElixirsConsumed": 0,
      "ScrollsConsumed": 1,
      "HitsLanded": 10,
      "HitsMissed": 9,
      "HitsTaken": 11,
      "CellsMoved": 147
    },
    {
      "TreasuresCollected": 0,
      "MaxLevelReached": 1,
      "EnemiesDefeated": 0,
      "FoodConsumed": 0,
      "ElixirsConsumed": 0,
      "ScrollsConsumed": 1,
      "HitsLanded": 11,
      "HitsMissed": 11,
      "HitsTaken": 11,
      "CellsMoved": 147
    },
    {
      "TreasuresCollected": 0,
      "MaxLevelReached": 1,
      "EnemiesDefeated": 0,
      "FoodConsumed": 0,
      "ElixirsConsumed": 0,
      "ScrollsConsumed": 1,
      "HitsLanded": 8,
      "HitsMissed": 10,
      "HitsTaken": 11,
      "CellsMoved": 147
    },
    {
      "TreasuresCollected": 0,
      "MaxLevelReached": 1,
      "EnemiesDefeated": 0,
      "FoodConsumed": 0,
      "ElixirsConsumed": 0,
      "ScrollsConsumed": 1,
      "HitsLanded": 9,
      "HitsMissed": 9,
      "HitsTaken": 11,
      "CellsMoved": 147
    },
    {
      "TreasuresCollected": 0,
      "MaxLevelReached": 1,
      "EnemiesDefeated": 0,
      "FoodConsumed": 0,
      "ElixirsConsumed": 0,
      "ScrollsConsumed": 1,
      "HitsLanded": 9,
      "HitsMissed": 10,
      "HitsTaken": 11,
      "CellsMoved": 147
    },
    {
      "TreasuresCollected": 0,
      "MaxLevelReached": 1,
      "EnemiesDefeated": 0,
      "FoodConsumed": 0,
      "ElixirsConsumed": 0,
      "ScrollsConsumed": 1,
      "HitsLanded": 10,
      "HitsMissed": 10,
      "HitsTaken": 11,
      "CellsMoved": 147
    },
    {
      "TreasuresCollected": 0,
      "MaxLevelReached": 1,
      "EnemiesDefeated": 0,
      "FoodConsumed": 0,
      "ElixirsConsumed": 0,
      "ScrollsConsumed": 1,
      "HitsLanded": 9,
      "HitsMissed": 12,
      "HitsTaken": 11,
      "CellsMoved": 147
    },
    {
      "TreasuresCollected": 0,
      "MaxLevelReached": 2,
      "EnemiesDefeated": 0,
      "FoodConsumed": 0,
      "ElixirsConsumed": 0,
      "ScrollsConsumed": 1,
      "HitsLanded": 17,
      "HitsMissed": 7,
      "HitsTaken": 11,
      "CellsMoved": 315
    }
  ]
}